runt/__init__.py
runt/runt.py
tests/__init__.py
tests/test_runt.py
runt-0.0.2.dist-info/LICENSE
runt-0.0.2.dist-info/METADATA
runt-0.0.2.dist-info/WHEEL
runt-0.0.2.dist-info/top_level.txt
runt-0.0.2.dist-info/RECORD
