Metadata-Version: 2.1
Name: runt
Version: 0.0.2
Summary: A job-managing task runner
Home-page: https://github.com/clayboone/runt.git
Author: Clay Boone
Author-email: tener.hades@gmail.com
License: UNKNOWN
Platform: UNKNOWN
